Workbook
Name Orden: 'Escalas y Matriz'!$A$23:$A$27
Name RiesgoValor: 'Escalas y Matriz'!$D$23:$D$27
Name MatrizRiesgo: 'Escalas y Matriz'!$B$32:$F$36

Sheet Portada
A1: PLANTILLA DE ANÁLISIS Y GESTIÓN DE RIESGOS - METODOLOGÍA MAGERIT
A3: Esta plantilla permite realizar un análisis de riesgos siguiendo la metodología MAGERIT (Metodología de Análisis y Gestión de Riesgos de los Sistemas de Información, CCN-CERT), ampliada con dos grupos de amenazas que no forman parte del catálogo original de 2012, para cubrir los riesgos de cadena de suministro y de inteligencia artificial.
A6: Contenido del libro
A7: 1. Amenazas MAGERIT
A8: Catálogo de referencia con las amenazas de los grupos N, I, E, A (catálogo oficial MAGERIT v3, Libro II) y los grupos ampliados S (cadena de suministro) e IA (inteligencia artificial), con descripción y salvaguardas orientativas.
A9: 2. Escalas y Matriz
A10: Definición de las escalas cualitativas de frecuencia, degradación/impacto y riesgo (MB/B/M/A/MA), y la matriz de riesgo 5x5 utilizada para calcular el nivel de riesgo.
A11: 3. Activos
A12: Inventario y valoración de los activos a analizar en las cinco dimensiones de seguridad de MAGERIT: Disponibilidad (D), Integridad (I), Confidencialidad (C), Autenticidad (A) y Trazabilidad (T).
A13: 4. Análisis y Tratamiento
A14: Registro principal: para cada activo y dimensión afectada, se selecciona una amenaza del catálogo, se valora la frecuencia y la degradación, se obtiene el nivel de riesgo (cálculo automático), se define el tratamiento y las salvaguardas, y se recalcula el riesgo residual.
A16: Cómo cumplimentar la plantilla
... A33: Fuente del catálogo de amenazas base (grupos N/I/E/A): CCN-CERT, MAGERIT v3 - Libro II, Catálogo de Elementos (reproducción autorizada citando la fuente). Grupos S e IA: ampliación elaborada para esta plantilla.

Sheet Amenazas MAGERIT
A1: Grupo | B1: Código | C1: Amenaza | D1: Descripción | E1: Salvaguardas orientativas
A2: N - Desastres naturales | B2: N.1 | C2: Fuego | D2: Incendio de origen natural (p. ej. incendio forestal) que puede destruir o dañar instalaciones, equipos o soportes de información. | E2: Disponer de sistemas de detección y extinción de incendios, ubicaciones alternativas (CPD de respaldo) y copias de seguridad externalizadas.
A3: N - Desastres naturales | B3: N.2 | C3: Daños por agua | D3: Inundación de origen natural (lluvias torrenciales, desbordamientos, etc.) que puede dañar instalaciones y equipos. | E3: Evitar ubicar los centros de proceso de datos en plantas bajas o zonas inundables; sistemas de detección de agua y planes de continuidad.
A4: N - Desastres naturales | B4: N.* | C4: Desastres naturales | D4: Otros desastres de origen natural: terremotos, rayos, meteorología adversa, etc. | E4: Análisis de riesgo geográfico de las instalaciones, seguro de daños y plan de continuidad de negocio (BCP/DRP).
A5: I - De origen industrial | B5: I.1 | C5: Fuego | D5: Incendio de origen industrial (fallo eléctrico, entorno del centro de proceso de datos, etc.). | E5: Sistemas de extinción automática, compartimentación de salas técnicas, mantenimiento eléctrico preventivo.
A6: I - De origen industrial | B6: I.2 | C6: Daños por agua | D6: Escapes, fugas o vertidos de agua de origen industrial (climatización, fontanería, sprinklers, etc.). | E6: Detección de fugas, ubicación de equipos elevada respecto al suelo, mantenimiento de instalaciones.
A7: I - De origen industrial | B7: I.* | C7: Desastres industriales | D7: Explosión, derrumbe, contaminación química, sobrecarga eléctrica u otros desastres de origen industrial (propios o del entorno). | E7: Planes de emergencia y evacuación, análisis de riesgos del entorno físico, coordinación con instalaciones colindantes.
A8: I - De origen industrial | B8: I.3 | C8: Contaminación mecánica | D8: Vibraciones, polvo o suciedad que afectan al funcionamiento de los equipos. | E8: Mantenimiento preventivo y salas técnicas con control ambiental adecuado.
A9: I - De origen industrial | B9: I.4 | C9: Contaminación electromagnética | D9: Interferencias electromagnéticas que afectan al funcionamiento de los equipos. | E9: Apantallamiento, cumplimiento de normativa de compatibilidad electromagnética y distancia a fuentes de interferencia.
A10: I - De origen industrial | B10: I.5 | C10: Avería de origen físico o lógico | D10: Fallo de un equipo o sistema por defecto de fabricación, desgaste o error de programación. | E10: Mantenimiento preventivo, redundancia de equipos críticos, pruebas y control de calidad del software.
A11: I - De origen industrial | B11: I.6 | C11: Corte del suministro eléctrico | D11: Cese de la alimentación eléctrica que puede afectar a la disponibilidad de los sistemas. | E11: SAI/UPS, generadores de respaldo y contratos con distribuidoras de doble acometida.
A12: I - De origen industrial | B12: I.7 | C12: Condiciones inadecuadas de temperatura o humedad | D12: Fallo de los sistemas de climatización que provoca condiciones ambientales fuera de rango en el centro de proceso de datos. | E12: Climatización redundante (N+1) y monitorización ambiental con alarmas.
... A84: IA - Riesgos de Inteligencia Artificial | B84: IA.14 | C84: Denegación de servicio del modelo | D84: Consultas diseñadas para consumir recursos computacionales excesivos (p. ej. «sponge examples») o saturar la capacidad del servicio de IA. | E84: Límites de tasa y de coste computacional por consulta, monitorización de consumo de recursos, y dimensionamiento y cuotas de uso.

Sheet Escalas y Matriz
A1: ESCALAS DE VALORACIÓN Y MATRIZ DE RIESGO - MAGERIT
A3: Escala de Frecuencia (probabilidad de ocurrencia)
A4: Abrev. | B4: Nombre | C4: Descripción
A5: MB | B5: Muy baja | C5: Muy poco frecuente: se estima que puede ocurrir cada varios años (frecuencia extraordinaria).
A6: B | B6: Baja | C6: Poco frecuente: se estima que puede ocurrir una vez al año.
A7: M | B7: Media | C7: Frecuencia normal: se estima que puede ocurrir varias veces al año.
A8: A | B8: Alta | C8: Frecuente: se estima que puede ocurrir mensualmente.
A9: MA | B9: Muy alta | C9: Muy frecuente: se estima que puede ocurrir semanal o diariamente.
A12: Escala de Degradación / Impacto
A13: Abrev. | B13: Nombre | C13: Descripción
A14: MB | B14: Muy bajo | C14: Degradación irrelevante del activo/dimensión de seguridad; consecuencias despreciables para la organización.
A15: B | B15: Bajo | C15: Degradación limitada; consecuencias menores, asumibles sin apenas gestión.
A16: M | B16: Medio | C16: Degradación significativa; consecuencias notables que requieren gestión activa.
A17: A | B17: Alto | C17: Degradación grave; consecuencias importantes, posible impacto legal/regulatorio o financiero relevante.
A18: MA | B18: Muy alto | C18: Degradación total/catastrófica; consecuencias críticas para la continuidad, reputación o supervivencia de la organización.
A21: Escala de Riesgo
A22: Abrev. | B22: Nombre | C22: Descripción | D22: Valor
A23: MB | B23: Riesgo muy bajo | C23: Riesgo muy bajo - asumible sin medidas adicionales. | D23: 0
A24: B | B24: Riesgo bajo | C24: Riesgo bajo - asumible, revisar periódicamente. | D24: 1
A25: M | B25: Riesgo medio | C25: Riesgo medio - requiere tratamiento planificado. | D25: 2
A26: A | B26: Riesgo alto | C26: Riesgo alto - inaceptable, requiere tratamiento prioritario. | D26: 3
A27: MA | B27: Riesgo muy alto | C27: Riesgo muy alto - inaceptable, requiere tratamiento inmediato / escalado a dirección. | D27: 4
A30: Matriz de riesgo (filas = Frecuencia, columnas = Degradación/Impacto)
A31: Frecuencia \ Impacto | B31: MB | C31: B | D31: M | E31: A | F31: MA
A32: MB | B32: MB | C32: MB | D32: B | E32: B | F32: B
A33: B | B33: MB | C33: B | D33: B | E33: M | F33: M
A34: M | B34: B | C34: B | D34: M | E34: A | F34: A
A35: A | B35: B | C35: M | D35: A | E35: A | F35: MA
A36: MA | B36: M | C36: A | D36: A | E36: MA | F36: MA
A38: Nota: esta matriz es una adaptación cualitativa (escala MB/B/M/A/MA) del cálculo detallado de MAGERIT (riesgo = valor del activo x degradación x frecuencia), pensada para una valoración ágil y homogénea en este registro de riesgos.

Sheet Activos
A1: ID | B1: Activo | C1: Tipo de activo | D1: Propietario / Responsable | E1: Descripción | F1: Valor D (Disponibilidad) | G1: Valor I (Integridad) | H1: Valor C (Confidencialidad) | I1: Valor A (Autenticidad) | J1: Valor T (Trazabilidad) | K1: Valor global
A2: AC-01 | B2: Base de datos de clientes (CRM) | C2: Información / Datos | D2: Responsable de Sistemas | E2: Datos personales y contractuales de clientes | F2: 8 | G2: 8 | H2: 9 | I2: 6 | J2: 6 | K2: =MAX(F2:J2)
A3: AC-02 | B3: Servidor de aplicaciones de producción | C3: Hardware / Equipamiento | D3: Responsable de Infraestructura | E3: Servidor físico/virtual que aloja las aplicaciones críticas | F3: 8 | G3: 6 | H3: 5 | I3: 5 | J3: 5 | K3: =MAX(F3:J3)
A4: AC-03 | B4: Código fuente de la aplicación principal | C4: Software / Aplicación | D4: Responsable de Desarrollo | E4: Repositorio de código de la aplicación de negocio | F4: 5 | G4: 8 | H4: 6 | I4: 5 | J4: 4 | K4: =MAX(F4:J4)
A5: AC-04 | B5: Servicio de infraestructura en la nube (IaaS) | C5: Servicio en la nube | D5: Responsable de Sistemas | E5: Proveedor de infraestructura cloud que aloja los servicios | F5: 8 | G5: 7 | H5: 6 | I5: 5 | J5: 5 | K5: =MAX(F5:J5)
A6: AC-05 | B6: Librería / componente de código abierto X | C6: Software / Aplicación | D6: Responsable de Desarrollo | E6: Componente de terceros integrado en la aplicación principal | F6: 4 | G6: 7 | H6: 4 | I6: 3 | J6: 3 | K6: =MAX(F6:J6)
A7: AC-06 | B7: Proveedor de servicios gestionados (MSP) | C7: Proveedor / Subcontratista | D7: Responsable de Compras/TI | E7: Subcontratista con acceso remoto para mantenimiento de sistemas | F7: 6 | G7: 6 | H7: 8 | I7: 6 | J7: 6 | K7: =MAX(F7:J7)
A8: AC-07 | B8: Modelo de IA de scoring de riesgo / chatbot | C8: Modelo o sistema de IA | D8: Responsable de Datos/IA | E8: Sistema de IA generativa o de scoring usado en procesos de negocio | F8: 6 | G8: 8 | H8: 7 | I8: 6 | J8: 5 | K8: =MAX(F8:J8)
A9: AC-08 | B9: Personal del departamento de TI | C9: Personal | D9: Dirección de TI | E9: Equipo responsable de operar y mantener los sistemas | F9: 7 | G9: 5 | H9: 5 | I9: 4 | J9: 4 | K9: =MAX(F9:J9)
A10: AC-09 | B10: Centro de proceso de datos (CPD) | C10: Instalaciones | D10: Responsable de Infraestructura | E10: Instalación física donde se ubican los equipos críticos | F10: 9 | G10: 6 | H10: 5 | I10: 4 | J10: 4 | K10: =MAX(F10:J10)
A11: =IF(B11="","","AC-"&TEXT(ROW()-1,"00")) | K11: =IF(B11="","",MAX(F11:J11))
A12: =IF(B12="","","AC-"&TEXT(ROW()-1,"00")) | K12: =IF(B12="","",MAX(F12:J12))
A13: =IF(B13="","","AC-"&TEXT(ROW()-1,"00")) | K13: =IF(B13="","",MAX(F13:J13))
A14: =IF(B14="","","AC-"&TEXT(ROW()-1,"00")) | K14: =IF(B14="","",MAX(F14:J14))
A15: =IF(B15="","","AC-"&TEXT(ROW()-1,"00")) | K15: =IF(B15="","",MAX(F15:J15))
A16: =IF(B16="","","AC-"&TEXT(ROW()-1,"00")) | K16: =IF(B16="","",MAX(F16:J16))
A17: =IF(B17="","","AC-"&TEXT(ROW()-1,"00")) | K17: =IF(B17="","",MAX(F17:J17))
A18: =IF(B18="","","AC-"&TEXT(ROW()-1,"00")) | K18: =IF(B18="","",MAX(F18:J18))
A19: =IF(B19="","","AC-"&TEXT(ROW()-1,"00")) | K19: =IF(B19="","",MAX(F19:J19))
A20: =IF(B20="","","AC-"&TEXT(ROW()-1,"00")) | K20: =IF(B20="","",MAX(F20:J20))
A21: =IF(B21="","","AC-"&TEXT(ROW()-1,"00")) | K21: =IF(B21="","",MAX(F21:J21))
A22: =IF(B22="","","AC-"&TEXT(ROW()-1,"00")) | K22: =IF(B22="","",MAX(F22:J22))
... A25: =IF(B25="","","AC-"&TEXT(ROW()-1,"00")) | K25: =IF(B25="","",MAX(F25:J25))
A27: Escala de valoración: 1-2 Muy bajo (MB) · 3-4 Bajo (B) · 5-6 Medio (M) · 7-8 Alto (A) · 9-10 Muy alto (MA).

Sheet Análisis y Tratamiento
A1: ID Riesgo | B1: Activo | C1: Dimensión afectada | D1: Valor del activo | E1: Código de amenaza | F1: Grupo de amenaza | G1: Amenaza | H1: Descripción de la amenaza | I1: Vulnerabilidad / Causa | J1: Salvaguardas existentes | K1: Frecuencia | L1: Degradación / Impacto | M1: Nivel de Riesgo (intrínseco) | N1: Tratamiento propuesto | O1: Salvaguardas adicionales propuestas | P1: Frecuencia residual | Q1: Degradación / Impacto residual | R1: Nivel de Riesgo residual | S1: Responsable | T1: Fecha límite | U1: Estado
A2: R-01 | B2: Base de datos de clientes (CRM) | C2: C | D2: =IFERROR(INDEX(Activos!$F$2:$J$25,MATCH($B2,Activos!$B$2:$B$25,0),MATCH($C2,{"D","I","C","A","T"},0)),"") | E2: A.11 | F2: =IFERROR(INDEX(Amenazas MAGERIT!$A$2:$A$84,MATCH($E2,Amenazas MAGERIT!$B$2:$B$84,0)),"") | G2: =IFERROR(VLOOKUP($E2,Amenazas MAGERIT!$B$2:$D$84,2,FALSE),"") | H2: =IFERROR(VLOOKUP($E2,Amenazas MAGERIT!$B$2:$D$84,3,FALSE),"") | I2: Contraseñas débiles y ausencia de MFA en el acceso a la base de datos. | J2: Control de acceso basado en roles. | K2: M | L2: A | M2: =IFERROR(INDEX(MatrizRiesgo,MATCH($K2,Orden,0),MATCH($L2,Orden,0)),"") | N2: Mitigar | O2: Implantar autenticación multifactor y monitorización de accesos. | P2: B | Q2: M | R2: =IFERROR(INDEX(MatrizRiesgo,MATCH($P2,Orden,0),MATCH($Q2,Orden,0)),"") | S2: Responsable de Sistemas | T2: 2026-09-30 | U2: En curso
A3: R-02 | B3: Servidor de aplicaciones de producción | C3: D | D3: =IFERROR(INDEX(Activos!$F$2:$J$25,MATCH($B3,Activos!$B$2:$B$25,0),MATCH($C3,{"D","I","C","A","T"},0)),"") | E3: I.6 | F3: =IFERROR(INDEX(Amenazas MAGERIT!$A$2:$A$84,MATCH($E3,Amenazas MAGERIT!$B$2:$B$84,0)),"") | G3: =IFERROR(VLOOKUP($E3,Amenazas MAGERIT!$B$2:$D$84,2,FALSE),"") | H3: =IFERROR(VLOOKUP($E3,Amenazas MAGERIT!$B$2:$D$84,3,FALSE),"") | I3: Ausencia de SAI redundante. | J3: SAI básico instalado. | K3: B | L3: A | M3: =IFERROR(INDEX(MatrizRiesgo,MATCH($K3,Orden,0),MATCH($L3,Orden,0)),"") | N3: Mitigar | O3: Instalar generador de respaldo y SAI redundante N+1. | P3: MB | Q3: M | R3: =IFERROR(INDEX(MatrizRiesgo,MATCH($P3,Orden,0),MATCH($Q3,Orden,0)),"") | S3: Responsable de Infraestructura | T3: 2026-10-31 | U3: Pendiente
A4: R-03 | B4: Servidor de aplicaciones de producción | C4: D | D4: =IFERROR(INDEX(Activos!$F$2:$J$25,MATCH($B4,Activos!$B$2:$B$25,0),MATCH($C4,{"D","I","C","A","T"},0)),"") | E4: A.24 | F4: =IFERROR(INDEX(Amenazas MAGERIT!$A$2:$A$84,MATCH($E4,Amenazas MAGERIT!$B$2:$B$84,0)),"") | G4: =IFERROR(VLOOKUP($E4,Amenazas MAGERIT!$B$2:$D$84,2,FALSE),"") | H4: =IFERROR(VLOOKUP($E4,Amenazas MAGERIT!$B$2:$D$84,3,FALSE),"") | I4: Sin protección anti-DDoS contratada. | J4: Firewall perimetral básico. | K4: M | L4: A | M4: =IFERROR(INDEX(MatrizRiesgo,MATCH($K4,Orden,0),MATCH($L4,Orden,0)),"") | N4: Mitigar | O4: Contratar servicio anti-DDoS gestionado. | P4: B | Q4: M | R4: =IFERROR(INDEX(MatrizRiesgo,MATCH($P4,Orden,0),MATCH($Q4,Orden,0)),"") | S4: Responsable de Infraestructura | T4: 2026-09-15 | U4: En curso
A5: R-04 | B5: Código fuente de la aplicación principal | C5: I | D5: =IFERROR(INDEX(Activos!$F$2:$J$25,MATCH($B5,Activos!$B$2:$B$25,0),MATCH($C5,{"D","I","C","A","T"},0)),"") | E5: E.20 | F5: =IFERROR(INDEX(Amenazas MAGERIT!$A$2:$A$84,MATCH($E5,Amenazas MAGERIT!$B$2:$B$84,0)),"") | G5: =IFERROR(VLOOKUP($E5,Amenazas MAGERIT!$B$2:$D$84,2,FALSE),"") | H5: =IFERROR(VLOOKUP($E5,Amenazas MAGERIT!$B$2:$D$84,3,FALSE),"") | I5: No se ejecuta análisis estático de código en el pipeline de CI/CD. | J5: Revisión manual de código por pares. | K5: A | L5: M | M5: =IFERROR(INDEX(MatrizRiesgo,MATCH($K5,Orden,0),MATCH($L5,Orden,0)),"") | N5: Mitigar | O5: Integrar SAST/SCA en el pipeline de CI/CD. | P5: M | Q5: B | R5: =IFERROR(INDEX(MatrizRiesgo,MATCH($P5,Orden,0),MATCH($Q5,Orden,0)),"") | S5: Responsable de Desarrollo | T5: 2026-09-30 | U5: En curso
A6: R-05 | B6: Servicio de infraestructura en la nube (IaaS) | C6: D | D6: =IFERROR(INDEX(Activos!$F$2:$J$25,MATCH($B6,Activos!$B$2:$B$25,0),MATCH($C6,{"D","I","C","A","T"},0)),"") | E6: S.5 | F6: =IFERROR(INDEX(Amenazas MAGERIT!$A$2:$A$84,MATCH($E6,Amenazas MAGERIT!$B$2:$B$84,0)),"") | G6: =IFERROR(VLOOKUP($E6,Amenazas MAGERIT!$B$2:$D$84,2,FALSE),"") | H6: =IFERROR(VLOOKUP($E6,Amenazas MAGERIT!$B$2:$D$84,3,FALSE),"") | I6: Dependencia de un único proveedor cloud sin plan de contingencia. | J6: SLA contractual del 99,9%. | K6: B | L6: A | M6: =IFERROR(INDEX(MatrizRiesgo,MATCH($K6,Orden,0),MATCH($L6,Orden,0)),"") | N6: Mitigar | O6: Definir plan de contingencia y evaluar arquitectura multicloud para servicios críticos. | P6: MB | Q6: M | R6: =IFERROR(INDEX(MatrizRiesgo,MATCH($P6,Orden,0),MATCH($Q6,Orden,0)),"") | S6: Responsable de Sistemas | T6: 2026-12-31 | U6: Pendiente
A7: R-06 | B7: Servicio de infraestructura en la nube (IaaS) | C7: C | D7: =IFERROR(INDEX(Activos!$F$2:$J$25,MATCH($B7,Activos!$B$2:$B$25,0),MATCH($C7,{"D","I","C","A","T"},0)),"") | E7: S.9 | F7: =IFERROR(INDEX(Amenazas MAGERIT!$A$2:$A$84,MATCH($E7,Amenazas MAGERIT!$B$2:$B$84,0)),"") | G7: =IFERROR(VLOOKUP($E7,Amenazas MAGERIT!$B$2:$D$84,2,FALSE),"") | H7: =IFERROR(VLOOKUP($E7,Amenazas MAGERIT!$B$2:$D$84,3,FALSE),"") | I7: Cifrado gestionado por el proveedor con claves del propio proveedor. | J7: Certificación ISO 27001 del proveedor. | K7: B | L7: MA | M7: =IFERROR(INDEX(MatrizRiesgo,MATCH($K7,Orden,0),MATCH($L7,Orden,0)),"") | N7: Mitigar | O7: Cifrar los datos con claves propias (BYOK) antes de subirlos a la nube. | P7: MB | Q7: A | R7: =IFERROR(INDEX(MatrizRiesgo,MATCH($P7,Orden,0),MATCH($Q7,Orden,0)),"") | S7: Responsable de Sistemas | T7: 2026-11-30 | U7: Pendiente
A8: R-07 | B8: Librería / componente de código abierto X | C8: I | D8: =IFERROR(INDEX(Activos!$F$2:$J$25,MATCH($B8,Activos!$B$2:$B$25,0),MATCH($C8,{"D","I","C","A","T"},0)),"") | E8: S.4 | F8: =IFERROR(INDEX(Amenazas MAGERIT!$A$2:$A$84,MATCH($E8,Amenazas MAGERIT!$B$2:$B$84,0)),"") | G8: =IFERROR(VLOOKUP($E8,Amenazas MAGERIT!$B$2:$D$84,2,FALSE),"") | H8: =IFERROR(VLOOKUP($E8,Amenazas MAGERIT!$B$2:$D$84,3,FALSE),"") | I8: No existe inventario (SBOM) de dependencias ni alertas de vulnerabilidades. | J8: Actualización manual esporádica. | K8: A | L8: M | M8: =IFERROR(INDEX(MatrizRiesgo,MATCH($K8,Orden,0),MATCH($L8,Orden,0)),"") | N8: Mitigar | O8: Implantar herramienta de análisis de composición de software (SCA) y generar SBOM. | P8: B | Q8: B | R8: =IFERROR(INDEX(MatrizRiesgo,MATCH($P8,Orden,0),MATCH($Q8,Orden,0)),"") | S8: Responsable de Desarrollo | T8: 2026-09-30 | U8: En curso
A9: R-08 | B9: Proveedor de servicios gestionados (MSP) | C9: C | D9: =IFERROR(INDEX(Activos!$F$2:$J$25,MATCH($B9,Activos!$B$2:$B$25,0),MATCH($C9,{"D","I","C","A","T"},0)),"") | E9: S.6 | F9: =IFERROR(INDEX(Amenazas MAGERIT!$A$2:$A$84,MATCH($E9,Amenazas MAGERIT!$B$2:$B$84,0)),"") | G9: =IFERROR(VLOOKUP($E9,Amenazas MAGERIT!$B$2:$D$84,2,FALSE),"") | H9: =IFERROR(VLOOKUP($E9,Amenazas MAGERIT!$B$2:$D$84,3,FALSE),"") | I9: Cláusulas contractuales de confidencialidad genéricas. | J9: Acuerdo de confidencialidad (NDA) firmado. | K9: B | L9: A | M9: =IFERROR(INDEX(MatrizRiesgo,MATCH($K9,Orden,0),MATCH($L9,Orden,0)),"") | N9: Mitigar | O9: Auditoría de seguridad anual al proveedor y cláusulas específicas de protección de datos. | P9: MB | Q9: M | R9: =IFERROR(INDEX(MatrizRiesgo,MATCH($P9,Orden,0),MATCH($Q9,Orden,0)),"") | S9: Responsable de Compras/TI | T9: 2026-10-15 | U9: Pendiente
A10: R-09 | B10: Proveedor de servicios gestionados (MSP) | C10: D | D10: =IFERROR(INDEX(Activos!$F$2:$J$25,MATCH($B10,Activos!$B$2:$B$25,0),MATCH($C10,{"D","I","C","A","T"},0)),"") | E10: S.12 | F10: =IFERROR(INDEX(Amenazas MAGERIT!$A$2:$A$84,MATCH($E10,Amenazas MAGERIT!$B$2:$B$84,0)),"") | G10: =IFERROR(VLOOKUP($E10,Amenazas MAGERIT!$B$2:$D$84,2,FALSE),"") | H10: =IFERROR(VLOOKUP($E10,Amenazas MAGERIT!$B$2:$D$84,3,FALSE),"") | I10: Accesos remotos permanentes sin MFA ni supervisión de sesión. | J10: VPN con usuario y contraseña. | K10: M | L10: A | M10: =IFERROR(INDEX(MatrizRiesgo,MATCH($K10,Orden,0),MATCH($L10,Orden,0)),"") | N10: Mitigar | O10: Implantar MFA, sesiones supervisadas y revocación automática de accesos. | P10: B | Q10: M | R10: =IFERROR(INDEX(MatrizRiesgo,MATCH($P10,Orden,0),MATCH($Q10,Orden,0)),"") | S10: Responsable de Sistemas | T10: 2026-09-30 | U10: En curso
A11: R-10 | B11: Modelo de IA de scoring de riesgo / chatbot | C11: I | D11: =IFERROR(INDEX(Activos!$F$2:$J$25,MATCH($B11,Activos!$B$2:$B$25,0),MATCH($C11,{"D","I","C","A","T"},0)),"") | E11: IA.1 | F11: =IFERROR(INDEX(Amenazas MAGERIT!$A$2:$A$84,MATCH($E11,Amenazas MAGERIT!$B$2:$B$84,0)),"") | G11: =IFERROR(VLOOKUP($E11,Amenazas MAGERIT!$B$2:$D$84,2,FALSE),"") | H11: =IFERROR(VLOOKUP($E11,Amenazas MAGERIT!$B$2:$D$84,3,FALSE),"") | I11: Datos de entrenamiento sin validación de procedencia. | J11: Ninguna específica. | K11: B | L11: A | M11: =IFERROR(INDEX(MatrizRiesgo,MATCH($K11,Orden,0),MATCH($L11,Orden,0)),"") | N11: Mitigar | O11: Validar el linaje de los datos de entrenamiento y detectar anomalías antes de reentrenar. | P11: MB | Q11: M | R11: =IFERROR(INDEX(MatrizRiesgo,MATCH($P11,Orden,0),MATCH($Q11,Orden,0)),"") | S11: Responsable de Datos/IA | T11: 2026-11-30 | U11: Pendiente
A12: R-11 | B12: Modelo de IA de scoring de riesgo / chatbot | C12: C | D12: =IFERROR(INDEX(Activos!$F$2:$J$25,MATCH($B12,Activos!$B$2:$B$25,0),MATCH($C12,{"D","I","C","A","T"},0)),"") | E12: IA.3 | F12: =IFERROR(INDEX(Amenazas MAGERIT!$A$2:$A$84,MATCH($E12,Amenazas MAGERIT!$B$2:$B$84,0)),"") | G12: =IFERROR(VLOOKUP($E12,Amenazas MAGERIT!$B$2:$D$84,2,FALSE),"") | H12: =IFERROR(VLOOKUP($E12,Amenazas MAGERIT!$B$2:$D$84,3,FALSE),"") | I12: El asistente de IA tiene acceso a herramientas internas sin separación clara entre instrucciones y datos de usuario. | J12: Filtrado básico de palabras clave. | K12: A | L12: A | M12: =IFERROR(INDEX(MatrizRiesgo,MATCH($K12,Orden,0),MATCH($L12,Orden,0)),"") | N12: Mitigar | O12: Separar instrucciones de sistema y datos de usuario, aplicar mínimo privilegio a las herramientas invocables y validar salidas. | P12: M | Q12: M | R12: =IFERROR(INDEX(MatrizRiesgo,MATCH($P12,Orden,0),MATCH($Q12,Orden,0)),"") | S12: Responsable de Datos/IA | T12: 2026-10-31 | U12: En curso
A13: R-12 | B13: Modelo de IA de scoring de riesgo / chatbot | C13: I | D13: =IFERROR(INDEX(Activos!$F$2:$J$25,MATCH($B13,Activos!$B$2:$B$25,0),MATCH($C13,{"D","I","C","A","T"},0)),"") | E13: IA.6 | F13: =IFERROR(INDEX(Amenazas MAGERIT!$A$2:$A$84,MATCH($E13,Amenazas MAGERIT!$B$2:$B$84,0)),"") | G13: =IFERROR(VLOOKUP($E13,Amenazas MAGERIT!$B$2:$D$84,2,FALSE),"") | H13: =IFERROR(VLOOKUP($E13,Amenazas MAGERIT!$B$2:$D$84,3,FALSE),"") | I13: No se han realizado auditorías de sesgo del modelo de scoring. | J13: Revisión manual puntual. | K13: M | L13: A | M13: =IFERROR(INDEX(MatrizRiesgo,MATCH($K13,Orden,0),MATCH($L13,Orden,0)),"") | N13: Mitigar | O13: Realizar auditoría de sesgo e imparcialidad y evaluación de impacto conforme al Reglamento de IA de la UE. | P13: B | Q13: M | R13: =IFERROR(INDEX(MatrizRiesgo,MATCH($P13,Orden,0),MATCH($Q13,Orden,0)),"") | S13: Responsable de Datos/IA | T13: 2026-12-31 | U13: Pendiente
... A15: R-14 | B15: Centro de proceso de datos (CPD) | C15: D | D15: =IFERROR(INDEX(Activos!$F$2:$J$25,MATCH($B15,Activos!$B$2:$B$25,0),MATCH($C15,{"D","I","C","A","T"},0)),"") | E15: N.2 | F15: =IFERROR(INDEX(Amenazas MAGERIT!$A$2:$A$84,MATCH($E15,Amenazas MAGERIT!$B$2:$B$84,0)),"") | G15: =IFERROR(VLOOKUP($E15,Amenazas MAGERIT!$B$2:$D$84,2,FALSE),"") | H15: =IFERROR(VLOOKUP($E15,Amenazas MAGERIT!$B$2:$D$84,3,FALSE),"") | I15: CPD ubicado en planta baja de un edificio en zona con riesgo de inundación. | J15: Sistema de detección de agua básico. | K15: MB | L15: MA | M15: =IFERROR(INDEX(MatrizRiesgo,MATCH($K15,Orden,0),MATCH($L15,Orden,0)),"") | N15: Mitigar | O15: Evaluar reubicación de equipos críticos a planta superior y mejorar el plan de continuidad. | P15: MB | Q15: A | R15: =IFERROR(INDEX(MatrizRiesgo,MATCH($P15,Orden,0),MATCH($Q15,Orden,0)),"") | S15: Responsable de Infraestructura | T15: 2027-03-31 | U15: Pendiente
A16: =IF(B16="","","R-"&TEXT(ROW()-1,"00")) | D16: =IFERROR(INDEX(Activos!$F$2:$J$25,MATCH($B16,Activos!$B$2:$B$25,0),MATCH($C16,{"D","I","C","A","T"},0)),"") | F16: =IFERROR(INDEX(Amenazas MAGERIT!$A$2:$A$84,MATCH($E16,Amenazas MAGERIT!$B$2:$B$84,0)),"") | G16: =IFERROR(VLOOKUP($E16,Amenazas MAGERIT!$B$2:$D$84,2,FALSE),"") | H16: =IFERROR(VLOOKUP($E16,Amenazas MAGERIT!$B$2:$D$84,3,FALSE),"") | M16: =IFERROR(INDEX(MatrizRiesgo,MATCH($K16,Orden,0),MATCH($L16,Orden,0)),"") | R16: =IFERROR(INDEX(MatrizRiesgo,MATCH($P16,Orden,0),MATCH($Q16,Orden,0)),"")
A17: =IF(B17="","","R-"&TEXT(ROW()-1,"00")) | D17: =IFERROR(INDEX(Activos!$F$2:$J$25,MATCH($B17,Activos!$B$2:$B$25,0),MATCH($C17,{"D","I","C","A","T"},0)),"") | F17: =IFERROR(INDEX(Amenazas MAGERIT!$A$2:$A$84,MATCH($E17,Amenazas MAGERIT!$B$2:$B$84,0)),"") | G17: =IFERROR(VLOOKUP($E17,Amenazas MAGERIT!$B$2:$D$84,2,FALSE),"") | H17: =IFERROR(VLOOKUP($E17,Amenazas MAGERIT!$B$2:$D$84,3,FALSE),"") | M17: =IFERROR(INDEX(MatrizRiesgo,MATCH($K17,Orden,0),MATCH($L17,Orden,0)),"") | R17: =IFERROR(INDEX(MatrizRiesgo,MATCH($P17,Orden,0),MATCH($Q17,Orden,0)),"")
A18: =IF(B18="","","R-"&TEXT(ROW()-1,"00")) | D18: =IFERROR(INDEX(Activos!$F$2:$J$25,MATCH($B18,Activos!$B$2:$B$25,0),MATCH($C18,{"D","I","C","A","T"},0)),"") | F18: =IFERROR(INDEX(Amenazas MAGERIT!$A$2:$A$84,MATCH($E18,Amenazas MAGERIT!$B$2:$B$84,0)),"") | G18: =IFERROR(VLOOKUP($E18,Amenazas MAGERIT!$B$2:$D$84,2,FALSE),"") | H18: =IFERROR(VLOOKUP($E18,Amenazas MAGERIT!$B$2:$D$84,3,FALSE),"") | M18: =IFERROR(INDEX(MatrizRiesgo,MATCH($K18,Orden,0),MATCH($L18,Orden,0)),"") | R18: =IFERROR(INDEX(MatrizRiesgo,MATCH($P18,Orden,0),MATCH($Q18,Orden,0)),"")
A19: =IF(B19="","","R-"&TEXT(ROW()-1,"00")) | D19: =IFERROR(INDEX(Activos!$F$2:$J$25,MATCH($B19,Activos!$B$2:$B$25,0),MATCH($C19,{"D","I","C","A","T"},0)),"") | F19: =IFERROR(INDEX(Amenazas MAGERIT!$A$2:$A$84,MATCH($E19,Amenazas MAGERIT!$B$2:$B$84,0)),"") | G19: =IFERROR(VLOOKUP($E19,Amenazas MAGERIT!$B$2:$D$84,2,FALSE),"") | H19: =IFERROR(VLOOKUP($E19,Amenazas MAGERIT!$B$2:$D$84,3,FALSE),"") | M19: =IFERROR(INDEX(MatrizRiesgo,MATCH($K19,Orden,0),MATCH($L19,Orden,0)),"") | R19: =IFERROR(INDEX(MatrizRiesgo,MATCH($P19,Orden,0),MATCH($Q19,Orden,0)),"")
A20: =IF(B20="","","R-"&TEXT(ROW()-1,"00")) | D20: =IFERROR(INDEX(Activos!$F$2:$J$25,MATCH($B20,Activos!$B$2:$B$25,0),MATCH($C20,{"D","I","C","A","T"},0)),"") | F20: =IFERROR(INDEX(Amenazas MAGERIT!$A$2:$A$84,MATCH($E20,Amenazas MAGERIT!$B$2:$B$84,0)),"") | G20: =IFERROR(VLOOKUP($E20,Amenazas MAGERIT!$B$2:$D$84,2,FALSE),"") | H20: =IFERROR(VLOOKUP($E20,Amenazas MAGERIT!$B$2:$D$84,3,FALSE),"") | M20: =IFERROR(INDEX(MatrizRiesgo,MATCH($K20,Orden,0),MATCH($L20,Orden,0)),"") | R20: =IFERROR(INDEX(MatrizRiesgo,MATCH($P20,Orden,0),MATCH($Q20,Orden,0)),"")
A21: =IF(B21="","","R-"&TEXT(ROW()-1,"00")) | D21: =IFERROR(INDEX(Activos!$F$2:$J$25,MATCH($B21,Activos!$B$2:$B$25,0),MATCH($C21,{"D","I","C","A","T"},0)),"") | F21: =IFERROR(INDEX(Amenazas MAGERIT!$A$2:$A$84,MATCH($E21,Amenazas MAGERIT!$B$2:$B$84,0)),"") | G21: =IFERROR(VLOOKUP($E21,Amenazas MAGERIT!$B$2:$D$84,2,FALSE),"") | H21: =IFERROR(VLOOKUP($E21,Amenazas MAGERIT!$B$2:$D$84,3,FALSE),"") | M21: =IFERROR(INDEX(MatrizRiesgo,MATCH($K21,Orden,0),MATCH($L21,Orden,0)),"") | R21: =IFERROR(INDEX(MatrizRiesgo,MATCH($P21,Orden,0),MATCH($Q21,Orden,0)),"")
A22: =IF(B22="","","R-"&TEXT(ROW()-1,"00")) | D22: =IFERROR(INDEX(Activos!$F$2:$J$25,MATCH($B22,Activos!$B$2:$B$25,0),MATCH($C22,{"D","I","C","A","T"},0)),"") | F22: =IFERROR(INDEX(Amenazas MAGERIT!$A$2:$A$84,MATCH($E22,Amenazas MAGERIT!$B$2:$B$84,0)),"") | G22: =IFERROR(VLOOKUP($E22,Amenazas MAGERIT!$B$2:$D$84,2,FALSE),"") | H22: =IFERROR(VLOOKUP($E22,Amenazas MAGERIT!$B$2:$D$84,3,FALSE),"") | M22: =IFERROR(INDEX(MatrizRiesgo,MATCH($K22,Orden,0),MATCH($L22,Orden,0)),"") | R22: =IFERROR(INDEX(MatrizRiesgo,MATCH($P22,Orden,0),MATCH($Q22,Orden,0)),"")
A23: =IF(B23="","","R-"&TEXT(ROW()-1,"00")) | D23: =IFERROR(INDEX(Activos!$F$2:$J$25,MATCH($B23,Activos!$B$2:$B$25,0),MATCH($C23,{"D","I","C","A","T"},0)),"") | F23: =IFERROR(INDEX(Amenazas MAGERIT!$A$2:$A$84,MATCH($E23,Amenazas MAGERIT!$B$2:$B$84,0)),"") | G23: =IFERROR(VLOOKUP($E23,Amenazas MAGERIT!$B$2:$D$84,2,FALSE),"") | H23: =IFERROR(VLOOKUP($E23,Amenazas MAGERIT!$B$2:$D$84,3,FALSE),"") | M23: =IFERROR(INDEX(MatrizRiesgo,MATCH($K23,Orden,0),MATCH($L23,Orden,0)),"") | R23: =IFERROR(INDEX(MatrizRiesgo,MATCH($P23,Orden,0),MATCH($Q23,Orden,0)),"")
A24: =IF(B24="","","R-"&TEXT(ROW()-1,"00")) | D24: =IFERROR(INDEX(Activos!$F$2:$J$25,MATCH($B24,Activos!$B$2:$B$25,0),MATCH($C24,{"D","I","C","A","T"},0)),"") | F24: =IFERROR(INDEX(Amenazas MAGERIT!$A$2:$A$84,MATCH($E24,Amenazas MAGERIT!$B$2:$B$84,0)),"") | G24: =IFERROR(VLOOKUP($E24,Amenazas MAGERIT!$B$2:$D$84,2,FALSE),"") | H24: =IFERROR(VLOOKUP($E24,Amenazas MAGERIT!$B$2:$D$84,3,FALSE),"") | M24: =IFERROR(INDEX(MatrizRiesgo,MATCH($K24,Orden,0),MATCH($L24,Orden,0)),"") | R24: =IFERROR(INDEX(MatrizRiesgo,MATCH($P24,Orden,0),MATCH($Q24,Orden,0)),"")
A25: =IF(B25="","","R-"&TEXT(ROW()-1,"00")) | D25: =IFERROR(INDEX(Activos!$F$2:$J$25,MATCH($B25,Activos!$B$2:$B$25,0),MATCH($C25,{"D","I","C","A","T"},0)),"") | F25: =IFERROR(INDEX(Amenazas MAGERIT!$A$2:$A$84,MATCH($E25,Amenazas MAGERIT!$B$2:$B$84,0)),"") | G25: =IFERROR(VLOOKUP($E25,Amenazas MAGERIT!$B$2:$D$84,2,FALSE),"") | H25: =IFERROR(VLOOKUP($E25,Amenazas MAGERIT!$B$2:$D$84,3,FALSE),"") | M25: =IFERROR(INDEX(MatrizRiesgo,MATCH($K25,Orden,0),MATCH($L25,Orden,0)),"") | R25: =IFERROR(INDEX(MatrizRiesgo,MATCH($P25,Orden,0),MATCH($Q25,Orden,0)),"")
A26: =IF(B26="","","R-"&TEXT(ROW()-1,"00")) | D26: =IFERROR(INDEX(Activos!$F$2:$J$25,MATCH($B26,Activos!$B$2:$B$25,0),MATCH($C26,{"D","I","C","A","T"},0)),"") | F26: =IFERROR(INDEX(Amenazas MAGERIT!$A$2:$A$84,MATCH($E26,Amenazas MAGERIT!$B$2:$B$84,0)),"") | G26: =IFERROR(VLOOKUP($E26,Amenazas MAGERIT!$B$2:$D$84,2,FALSE),"") | H26: =IFERROR(VLOOKUP($E26,Amenazas MAGERIT!$B$2:$D$84,3,FALSE),"") | M26: =IFERROR(INDEX(MatrizRiesgo,MATCH($K26,Orden,0),MATCH($L26,Orden,0)),"") | R26: =IFERROR(INDEX(MatrizRiesgo,MATCH($P26,Orden,0),MATCH($Q26,Orden,0)),"")
A27: =IF(B27="","","R-"&TEXT(ROW()-1,"00")) | D27: =IFERROR(INDEX(Activos!$F$2:$J$25,MATCH($B27,Activos!$B$2:$B$25,0),MATCH($C27,{"D","I","C","A","T"},0)),"") | F27: =IFERROR(INDEX(Amenazas MAGERIT!$A$2:$A$84,MATCH($E27,Amenazas MAGERIT!$B$2:$B$84,0)),"") | G27: =IFERROR(VLOOKUP($E27,Amenazas MAGERIT!$B$2:$D$84,2,FALSE),"") | H27: =IFERROR(VLOOKUP($E27,Amenazas MAGERIT!$B$2:$D$84,3,FALSE),"") | M27: =IFERROR(INDEX(MatrizRiesgo,MATCH($K27,Orden,0),MATCH($L27,Orden,0)),"") | R27: =IFERROR(INDEX(MatrizRiesgo,MATCH($P27,Orden,0),MATCH($Q27,Orden,0)),"")
... A35: =IF(B35="","","R-"&TEXT(ROW()-1,"00")) | D35: =IFERROR(INDEX(Activos!$F$2:$J$25,MATCH($B35,Activos!$B$2:$B$25,0),MATCH($C35,{"D","I","C","A","T"},0)),"") | F35: =IFERROR(INDEX(Amenazas MAGERIT!$A$2:$A$84,MATCH($E35,Amenazas MAGERIT!$B$2:$B$84,0)),"") | G35: =IFERROR(VLOOKUP($E35,Amenazas MAGERIT!$B$2:$D$84,2,FALSE),"") | H35: =IFERROR(VLOOKUP($E35,Amenazas MAGERIT!$B$2:$D$84,3,FALSE),"") | M35: =IFERROR(INDEX(MatrizRiesgo,MATCH($K35,Orden,0),MATCH($L35,Orden,0)),"") | R35: =IFERROR(INDEX(MatrizRiesgo,MATCH($P35,Orden,0),MATCH($Q35,Orden,0)),"")
A37: Notas: columnas D, F, G, H, M y R se calculan automáticamente (no editar). Complete únicamente las celdas con fondo amarillo. El Nivel de Riesgo Residual debe recalcularse tras implementar las salvaguardas adicionales propuestas.
